Workbook

Sheet 入力
A1: ブランズ中央林間 W-A（4LDK・92.2㎡）費用シミュレーション：入力シート
A2: 【使い方】青字・黄色セルが変更可能な入力値。変更すると全シートが自動再計算されます。
A3: ① 物件・購入条件
A4: 物件価格（円） | B4: 76000000 | D4: 営業提示価格（2026年8月時点）
A5: 頭金（円） | B5: 0 | D5: 0＝フルローン。頭金を入れると借入額が自動で減少
A6: 借入額（円） | B6: =B4-B5 -> 76000000 | D6: 自動計算：物件価格－頭金
A7: 返済期間（年） | B7: 35 | D7: 元利均等・ボーナス払いなし
A8: 入居年（西暦） | B8: 2026 | D8: 住宅ローン控除の起点
A10: ② 金利シナリオ（変動金利）
A11: 当初適用金利（年率） | B11: 0.01 | D11: 2026年8月時点の変動金利水準（メガバンク約1.08%・ネット系約0.9〜1.3%）
A12: 金利改定① 開始年目 | B12: 6 | D12: 日銀追加利上げを想定（野村證券予想：2026〜27年に+0.5%）
A13: 改定①後の金利 | B13: 0.015
A14: 金利改定② 開始年目 | B14: 11
A15: 改定②後の金利 | B15: 0.02 | D15: 上昇なしを見たい場合は①②とも当初金利と同じ値に
A17: ③ 毎月のランニングコスト（管理関連は営業提示の実費）
A18: 管理費（月額） | B18: 28500 | D18: 実費（営業提示）。92.2㎡→約309円/㎡：やや高め水準
A19: 管理費の年間上昇率 | B19: 0 | D19: 過去実績では10〜20年で1〜2割上昇する例も。保守的に見るなら1%
A20: 修繕積立金 第1段階（1年目〜・月額） | B20: 16600 | D20: 実費（営業提示）。92.2㎡→約180円/㎡
A21: 修繕積立金 第2段階：開始年目／月額 | B21: 6 | C21: 24900 | D21: 推定（一般的な段階増額計画×1.5倍）。長期修繕計画の実額に書き換えてください
A22: 修繕積立金 第3段階：開始年目／月額 | B22: 11 | C22: 33200 | D22: 推定（×2.0倍）
A23: 修繕積立金 第4段階：開始年目／月額 | B23: 16 | C23: 37400 | D23: 推定（×2.25倍）。国交省ガイドライン水準への到達を仮定
A24: テレビ利用料（月額） | B24: 330 | D24: 実費（営業提示）
A25: インターネット利用料（月額） | B25: 1100 | D25: 実費（営業提示・全戸一括型）
A27: ④ 税金（推定・納税通知書で要確認）
A28: 固定資産税・都市計画税 軽減中（年額） | B28: 220000 | D28: 推定。新築マンションは5年間 建物分1/2軽減
A29: 同 軽減終了後（年額） | B29: 300000 | D29: 推定
A30: 軽減年数 | B30: 5 | D30: 新築中高層耐火住宅は5年
A32: ⑤ 住宅ローン控除（2026年入居・新築）
A33: 控除率 | B33: 0.007 | D33: 2026年入居：0.7%
A34: 控除年数 | B34: 13 | D34: 新築は13年
A35: 借入限度額（円） | B35: 35000000 | D35: ZEH水準3,500万（一般世帯）。子育て・若者夫婦世帯は45,000,000に変更。省エネ基準止まりなら20,000,000。物件の省エネ区分は要確認
A37: ⑥ 年収・家計
A38: 年収（ローン名義人・初年度） | B38: 11000000 | D38: 額面。年次シートの年収列は個別年の上書きも可能
A39: 年収上昇率（年） | B39: 0.01 | D39: 昇給見込み。0%〜3%で感度を見る
A40: 手取り率（概算） | B40: 0.75 | D40: 額面→手取りの概算率

Sheet 初期費用
A1: 初期費用（購入時に必要な自己資金）の全洗い出し
A2: 項目 | B2: 金額（円） | C2: 料率等 | D2: 根拠・メモ（青字は変更可能な概算値）
A3: 頭金 | B3: =入力!B5 -> 0 | D3: 入力シート⑤と連動
A4: 修繕積立基金（引渡時一括） | B4: 1988800 | D4: 実費（営業提示）。一般的水準（50万円前後）より大幅に高い。その分、月額修繕積立金が抑えられている設計
A5: 管理準備金（引渡時一括） | B5: 28500 | D5: 実費（営業提示）
A6: 登記費用（保存・移転・抵当権＋司法書士報酬） | B6: 450000 | D6: 概算。司法書士見積で確定
A7: 融資事務手数料 | B7: =入力!B6*C7 -> 1672000 | C7: 0.022 | D7: 借入額×料率（ネット銀行標準2.20%）。保証料型の銀行なら料率を変更
A8: 印紙税（売買・ローン契約） | B8: 20000 | D8: 電子契約なら売買分は不要の場合あり
A9: 火災・地震保険（5年一括） | B9: 200000 | D9: 概算。補償内容により10〜30万円
A10: 固定資産税・都市計画税 清算金 | B10: 100000 | D10: 引渡日以降の日割分。概算
A11: 不動産取得税（軽減適用後） | B11: 0 | D11: 新築・床面積要件で軽減後0円と推定。要確認
A12: 引越し費用 | B12: 200000 | D12: 概算
A13: オプション・インテリア予備費 | B13: 500000 | D13: 食洗機・照明・カーテン等。交渉でサービス化を狙う項目
A14: 諸費用合計（頭金を除く） | B14: =SUM(B4:B13) -> 5159300
A15: 初期自己資金 合計（頭金＋諸費用） | B15: =B3+B14 -> 5159300 | D15: 当初想定の「諸費用400万円」を上回る点に注意（修繕積立基金約199万円が主因）

Sheet 月次返済
A1: 月 | B1: 年目 | C1: 適用金利(年率) | D1: 月初残高 | E1: 月返済額 | F1: うち利息 | G1: うち元金 | H1: 月末残高 | J1: ※金利は入力シート②のシナリオに従い年単位で切替。返済額は残高・残期間から毎月再計算（＝金利改定時に自動で返済額が変わる方式）
A2: 1 | B2: =INT((A2-1)/12)+1 -> 1 | C2: =IF(B2>=入力!$B$14,入力!$B$15,IF(B2>=入力!$B$12,入力!$B$13,入力!$B$11)) -> 0.01 | D2: =入力!$B$6 -> 76000000 | E2: =-PMT(C2/12,420-A2+1,D2) -> 214537.13 | F2: =D2*C2/12 -> 63333.333 | G2: =E2-F2 -> 151203.8 | H2: =D2-G2 -> 75848796
A3: 2 | B3: =INT((A3-1)/12)+1 -> 1 | C3: =IF(B3>=入力!$B$14,入力!$B$15,IF(B3>=入力!$B$12,入力!$B$13,入力!$B$11)) -> 0.01 | D3: =H2 -> 75848796 | E3: =-PMT(C3/12,420-A3+1,D3) -> 214537.13 | F3: =D3*C3/12 -> 63207.33 | G3: =E3-F3 -> 151329.8 | H3: =D3-G3 -> 75697466
A4: 3 | B4: =INT((A4-1)/12)+1 -> 1 | C4: =IF(B4>=入力!$B$14,入力!$B$15,IF(B4>=入力!$B$12,入力!$B$13,入力!$B$11)) -> 0.01 | D4: =H3 -> 75697466 | E4: =-PMT(C4/12,420-A4+1,D4) -> 214537.13 | F4: =D4*C4/12 -> 63081.222 | G4: =E4-F4 -> 151455.91 | H4: =D4-G4 -> 75546010
A5: 4 | B5: =INT((A5-1)/12)+1 -> 1 | C5: =IF(B5>=入力!$B$14,入力!$B$15,IF(B5>=入力!$B$12,入力!$B$13,入力!$B$11)) -> 0.01 | D5: =H4 -> 75546010 | E5: =-PMT(C5/12,420-A5+1,D5) -> 214537.13 | F5: =D5*C5/12 -> 62955.009 | G5: =E5-F5 -> 151582.12 | H5: =D5-G5 -> 75394428
A6: 5 | B6: =INT((A6-1)/12)+1 -> 1 | C6: =IF(B6>=入力!$B$14,入力!$B$15,IF(B6>=入力!$B$12,入力!$B$13,入力!$B$11)) -> 0.01 | D6: =H5 -> 75394428 | E6: =-PMT(C6/12,420-A6+1,D6) -> 214537.13 | F6: =D6*C6/12 -> 62828.69 | G6: =E6-F6 -> 151708.44 | H6: =D6-G6 -> 75242720
A7: 6 | B7: =INT((A7-1)/12)+1 -> 1 | C7: =IF(B7>=入力!$B$14,入力!$B$15,IF(B7>=入力!$B$12,入力!$B$13,入力!$B$11)) -> 0.01 | D7: =H6 -> 75242720 | E7: =-PMT(C7/12,420-A7+1,D7) -> 214537.13 | F7: =D7*C7/12 -> 62702.267 | G7: =E7-F7 -> 151834.86 | H7: =D7-G7 -> 75090885
A8: 7 | B8: =INT((A8-1)/12)+1 -> 1 | C8: =IF(B8>=入力!$B$14,入力!$B$15,IF(B8>=入力!$B$12,入力!$B$13,入力!$B$11)) -> 0.01 | D8: =H7 -> 75090885 | E8: =-PMT(C8/12,420-A8+1,D8) -> 214537.13 | F8: =D8*C8/12 -> 62575.738 | G8: =E8-F8 -> 151961.39 | H8: =D8-G8 -> 74938924
A9: 8 | B9: =INT((A9-1)/12)+1 -> 1 | C9: =IF(B9>=入力!$B$14,入力!$B$15,IF(B9>=入力!$B$12,入力!$B$13,入力!$B$11)) -> 0.01 | D9: =H8 -> 74938924 | E9: =-PMT(C9/12,420-A9+1,D9) -> 214537.13 | F9: =D9*C9/12 -> 62449.103 | G9: =E9-F9 -> 152088.03 | H9: =D9-G9 -> 74786836
A10: 9 | B10: =INT((A10-1)/12)+1 -> 1 | C10: =IF(B10>=入力!$B$14,入力!$B$15,IF(B10>=入力!$B$12,入力!$B$13,入力!$B$11)) -> 0.01 | D10: =H9 -> 74786836 | E10: =-PMT(C10/12,420-A10+1,D10) -> 214537.13 | F10: =D10*C10/12 -> 62322.363 | G10: =E10-F10 -> 152214.77 | H10: =D10-G10 -> 74634621
A11: 10 | B11: =INT((A11-1)/12)+1 -> 1 | C11: =IF(B11>=入力!$B$14,入力!$B$15,IF(B11>=入力!$B$12,入力!$B$13,入力!$B$11)) -> 0.01 | D11: =H10 -> 74634621 | E11: =-PMT(C11/12,420-A11+1,D11) -> 214537.13 | F11: =D11*C11/12 -> 62195.517 | G11: =E11-F11 -> 152341.61 | H11: =D11-G11 -> 74482279
A12: 11 | B12: =INT((A12-1)/12)+1 -> 1 | C12: =IF(B12>=入力!$B$14,入力!$B$15,IF(B12>=入力!$B$12,入力!$B$13,入力!$B$11)) -> 0.01 | D12: =H11 -> 74482279 | E12: =-PMT(C12/12,420-A12+1,D12) -> 214537.13 | F12: =D12*C12/12 -> 62068.566 | G12: =E12-F12 -> 152468.57 | H12: =D12-G12 -> 74329811
A13: 12 | B13: =INT((A13-1)/12)+1 -> 1 | C13: =IF(B13>=入力!$B$14,入力!$B$15,IF(B13>=入力!$B$12,入力!$B$13,入力!$B$11)) -> 0.01 | D13: =H12 -> 74329811 | E13: =-PMT(C13/12,420-A13+1,D13) -> 214537.13 | F13: =D13*C13/12 -> 61941.509 | G13: =E13-F13 -> 152595.62 | H13: =D13-G13 -> 74177215
A14: 13 | B14: =INT((A14-1)/12)+1 -> 2 | C14: =IF(B14>=入力!$B$14,入力!$B$15,IF(B14>=入力!$B$12,入力!$B$13,入力!$B$11)) -> 0.01 | D14: =H13 -> 74177215 | E14: =-PMT(C14/12,420-A14+1,D14) -> 214537.13 | F14: =D14*C14/12 -> 61814.346 | G14: =E14-F14 -> 152722.79 | H14: =D14-G14 -> 74024492
... A421: 420 | B421: =INT((A421-1)/12)+1 -> 35 | C421: =IF(B421>=入力!$B$14,入力!$B$15,IF(B421>=入力!$B$12,入力!$B$13,入力!$B$11)) -> 0.02 | D421: =H420 -> 243560.03 | E421: =-PMT(C421/12,420-A421+1,D421) -> 243965.96 | F421: =D421*C421/12 -> 405.93338 | G421: =E421-F421 -> 243560.03 | H421: =D421-G421 -> 0

Sheet 年次シミュレーション
A1: 年目 | B1: 西暦 | C1: 年収(額面)※上書き可 | D1: 手取り概算 | E1: 年間ローン返済 | F1: うち利息 | G1: 年末ローン残高 | H1: 控除額(残高基準) | I1: 課税所得概算 | J1: 所得税概算 | K1: 控除上限概算 | L1: 住宅ローン控除(適用額) | M1: 管理費(年) | N1: 修繕積立金(年) | O1: TV+ネット(年) | P1: 固定資産税等(年) | Q1: 年間住居費合計 | R1: 月平均住居費 | S1: 返済負担率(額面) | T1: 住居費/手取り | U1: 累計住居費
A2: 1 | B2: =入力!$B$8+A2-1 -> 2026 | C2: =入力!$B$38*(1+入力!$B$39)^(A2-1) -> 11000000 | D2: =C2*入力!$B$40 -> 8250000 | E2: =SUMIF(月次返済!$B$2:$B$421,A2,月次返済!$E$2:$E$421) -> 2574445.6 | F2: =SUMIF(月次返済!$B$2:$B$421,A2,月次返済!$F$2:$F$421) -> 751660.65 | G2: =INDEX(月次返済!$H$2:$H$421,A2*12) -> 74177215 | H2: =IF(A2<=入力!$B$34,MIN(G2,入力!$B$35)*入力!$B$33,0) -> 245000 | I2: =MAX(0,C2-MIN(1950000,MAX(550000,IF(C2<=1800000,C2*0.4-100000,IF(C2<=3600000,C2*0.3+80000,IF(C2<=6600000,C2*0.2+440000,IF(C2<=8500000,C2*0.1+1100000,1950000))))))-C2*0.145-480000) -> 6975000 | J2: =IF(I2<=1950000,I2*0.05,IF(I2<=3300000,I2*0.1-97500,IF(I2<=6950000,I2*0.2-427500,IF(I2<=9000000,I2*0.23-636000,IF(I2<=18000000,I2*0.33-1536000,I2*0.4-2796000))))) -> 968250 | K2: =J2+MIN(97500,I2*0.05) -> 1065750 | L2: =MIN(H2,K2) -> 245000 | M2: =12*入力!$B$18*(1+入力!$B$19)^(A2-1) -> 342000 | N2: =12*IF(A2>=入力!$B$23,入力!$C$23,IF(A2>=入力!$B$22,入力!$C$22,IF(A2>=入力!$B$21,入力!$C$21,入力!$B$20))) -> 199200 | O2: =12*(入力!$B$24+入力!$B$25) -> 17160 | P2: =IF(A2<=入力!$B$30,入力!$B$28,入力!$B$29) -> 220000 | Q2: =E2+M2+N2+O2+P2-L2 -> 3107805.6 | R2: =Q2/12 -> 258983.8 | S2: =IF(C2=0,0,E2/C2) -> 0.23404051 | T2: =IF(D2=0,0,Q2/D2) -> 0.37670371 | U2: =SUM($Q$2:Q2) -> 3107805.6
A3: 2 | B3: =入力!$B$8+A3-1 -> 2027 | C3: =入力!$B$38*(1+入力!$B$39)^(A3-1) -> 11110000 | D3: =C3*入力!$B$40 -> 8332500 | E3: =SUMIF(月次返済!$B$2:$B$421,A3,月次返済!$E$2:$E$421) -> 2574445.6 | F3: =SUMIF(月次返済!$B$2:$B$421,A3,月次返済!$F$2:$F$421) -> 733349.02 | G3: =INDEX(月次返済!$H$2:$H$421,A3*12) -> 72336119 | H3: =IF(A3<=入力!$B$34,MIN(G3,入力!$B$35)*入力!$B$33,0) -> 245000 | I3: =MAX(0,C3-MIN(1950000,MAX(550000,IF(C3<=1800000,C3*0.4-100000,IF(C3<=3600000,C3*0.3+80000,IF(C3<=6600000,C3*0.2+440000,IF(C3<=8500000,C3*0.1+1100000,1950000))))))-C3*0.145-480000) -> 7069050 | J3: =IF(I3<=1950000,I3*0.05,IF(I3<=3300000,I3*0.1-97500,IF(I3<=6950000,I3*0.2-427500,IF(I3<=9000000,I3*0.23-636000,IF(I3<=18000000,I3*0.33-1536000,I3*0.4-2796000))))) -> 989881.5 | K3: =J3+MIN(97500,I3*0.05) -> 1087381.5 | L3: =MIN(H3,K3) -> 245000 | M3: =12*入力!$B$18*(1+入力!$B$19)^(A3-1) -> 342000 | N3: =12*IF(A3>=入力!$B$23,入力!$C$23,IF(A3>=入力!$B$22,入力!$C$22,IF(A3>=入力!$B$21,入力!$C$21,入力!$B$20))) -> 199200 | O3: =12*(入力!$B$24+入力!$B$25) -> 17160 | P3: =IF(A3<=入力!$B$30,入力!$B$28,入力!$B$29) -> 220000 | Q3: =E3+M3+N3+O3+P3-L3 -> 3107805.6 | R3: =Q3/12 -> 258983.8 | S3: =IF(C3=0,0,E3/C3) -> 0.23172327 | T3: =IF(D3=0,0,Q3/D3) -> 0.37297397 | U3: =SUM($Q$2:Q3) -> 6215611.1
A4: 3 | B4: =入力!$B$8+A4-1 -> 2028 | C4: =入力!$B$38*(1+入力!$B$39)^(A4-1) -> 11221100 | D4: =C4*入力!$B$40 -> 8415825 | E4: =SUMIF(月次返済!$B$2:$B$421,A4,月次返済!$E$2:$E$421) -> 2574445.6 | F4: =SUMIF(月次返済!$B$2:$B$421,A4,月次返済!$F$2:$F$421) -> 714853.44 | G4: =INDEX(月次返済!$H$2:$H$421,A4*12) -> 70476526 | H4: =IF(A4<=入力!$B$34,MIN(G4,入力!$B$35)*入力!$B$33,0) -> 245000 | I4: =MAX(0,C4-MIN(1950000,MAX(550000,IF(C4<=1800000,C4*0.4-100000,IF(C4<=3600000,C4*0.3+80000,IF(C4<=6600000,C4*0.2+440000,IF(C4<=8500000,C4*0.1+1100000,1950000))))))-C4*0.145-480000) -> 7164040.5 | J4: =IF(I4<=1950000,I4*0.05,IF(I4<=3300000,I4*0.1-97500,IF(I4<=6950000,I4*0.2-427500,IF(I4<=9000000,I4*0.23-636000,IF(I4<=18000000,I4*0.33-1536000,I4*0.4-2796000))))) -> 1011729.3 | K4: =J4+MIN(97500,I4*0.05) -> 1109229.3 | L4: =MIN(H4,K4) -> 245000 | M4: =12*入力!$B$18*(1+入力!$B$19)^(A4-1) -> 342000 | N4: =12*IF(A4>=入力!$B$23,入力!$C$23,IF(A4>=入力!$B$22,入力!$C$22,IF(A4>=入力!$B$21,入力!$C$21,入力!$B$20))) -> 199200 | O4: =12*(入力!$B$24+入力!$B$25) -> 17160 | P4: =IF(A4<=入力!$B$30,入力!$B$28,入力!$B$29) -> 220000 | Q4: =E4+M4+N4+O4+P4-L4 -> 3107805.6 | R4: =Q4/12 -> 258983.8 | S4: =IF(C4=0,0,E4/C4) -> 0.22942898 | T4: =IF(D4=0,0,Q4/D4) -> 0.36928115 | U4: =SUM($Q$2:Q4) -> 9323416.7
A5: 4 | B5: =入力!$B$8+A5-1 -> 2029 | C5: =入力!$B$38*(1+入力!$B$39)^(A5-1) -> 11333311 | D5: =C5*入力!$B$40 -> 8499983.2 | E5: =SUMIF(月次返済!$B$2:$B$421,A5,月次返済!$E$2:$E$421) -> 2574445.6 | F5: =SUMIF(月次返済!$B$2:$B$421,A5,月次返済!$F$2:$F$421) -> 696172.05 | G5: =INDEX(月次返済!$H$2:$H$421,A5*12) -> 68598253 | H5: =IF(A5<=入力!$B$34,MIN(G5,入力!$B$35)*入力!$B$33,0) -> 245000 | I5: =MAX(0,C5-MIN(1950000,MAX(550000,IF(C5<=1800000,C5*0.4-100000,IF(C5<=3600000,C5*0.3+80000,IF(C5<=6600000,C5*0.2+440000,IF(C5<=8500000,C5*0.1+1100000,1950000))))))-C5*0.145-480000) -> 7259980.9 | J5: =IF(I5<=1950000,I5*0.05,IF(I5<=3300000,I5*0.1-97500,IF(I5<=6950000,I5*0.2-427500,IF(I5<=9000000,I5*0.23-636000,IF(I5<=18000000,I5*0.33-1536000,I5*0.4-2796000))))) -> 1033795.6 | K5: =J5+MIN(97500,I5*0.05) -> 1131295.6 | L5: =MIN(H5,K5) -> 245000 | M5: =12*入力!$B$18*(1+入力!$B$19)^(A5-1) -> 342000 | N5: =12*IF(A5>=入力!$B$23,入力!$C$23,IF(A5>=入力!$B$22,入力!$C$22,IF(A5>=入力!$B$21,入力!$C$21,入力!$B$20))) -> 199200 | O5: =12*(入力!$B$24+入力!$B$25) -> 17160 | P5: =IF(A5<=入力!$B$30,入力!$B$28,入力!$B$29) -> 220000 | Q5: =E5+M5+N5+O5+P5-L5 -> 3107805.6 | R5: =Q5/12 -> 258983.8 | S5: =IF(C5=0,0,E5/C5) -> 0.22715741 | T5: =IF(D5=0,0,Q5/D5) -> 0.36562491 | U5: =SUM($Q$2:Q5) -> 12431222
A6: 5 | B6: =入力!$B$8+A6-1 -> 2030 | C6: =入力!$B$38*(1+入力!$B$39)^(A6-1) -> 11446644 | D6: =C6*入力!$B$40 -> 8584983.1 | E6: =SUMIF(月次返済!$B$2:$B$421,A6,月次返済!$E$2:$E$421) -> 2574445.6 | F6: =SUMIF(月次返済!$B$2:$B$421,A6,月次返済!$F$2:$F$421) -> 677302.98 | G6: =INDEX(月次返済!$H$2:$H$421,A6*12) -> 66701110 | H6: =IF(A6<=入力!$B$34,MIN(G6,入力!$B$35)*入力!$B$33,0) -> 245000 | I6: =MAX(0,C6-MIN(1950000,MAX(550000,IF(C6<=1800000,C6*0.4-100000,IF(C6<=3600000,C6*0.3+80000,IF(C6<=6600000,C6*0.2+440000,IF(C6<=8500000,C6*0.1+1100000,1950000))))))-C6*0.145-480000) -> 7356880.7 | J6: =IF(I6<=1950000,I6*0.05,IF(I6<=3300000,I6*0.1-97500,IF(I6<=6950000,I6*0.2-427500,IF(I6<=9000000,I6*0.23-636000,IF(I6<=18000000,I6*0.33-1536000,I6*0.4-2796000))))) -> 1056082.6 | K6: =J6+MIN(97500,I6*0.05) -> 1153582.6 | L6: =MIN(H6,K6) -> 245000 | M6: =12*入力!$B$18*(1+入力!$B$19)^(A6-1) -> 342000 | N6: =12*IF(A6>=入力!$B$23,入力!$C$23,IF(A6>=入力!$B$22,入力!$C$22,IF(A6>=入力!$B$21,入力!$C$21,入力!$B$20))) -> 199200 | O6: =12*(入力!$B$24+入力!$B$25) -> 17160 | P6: =IF(A6<=入力!$B$30,入力!$B$28,入力!$B$29) -> 220000 | Q6: =E6+M6+N6+O6+P6-L6 -> 3107805.6 | R6: =Q6/12 -> 258983.8 | S6: =IF(C6=0,0,E6/C6) -> 0.22490833 | T6: =IF(D6=0,0,Q6/D6) -> 0.36200486 | U6: =SUM($Q$2:Q6) -> 15539028
A7: 6 | B7: =入力!$B$8+A7-1 -> 2031 | C7: =入力!$B$38*(1+入力!$B$39)^(A7-1) -> 11561111 | D7: =C7*入力!$B$40 -> 8670832.9 | E7: =SUMIF(月次返済!$B$2:$B$421,A7,月次返済!$E$2:$E$421) -> 2762388.1 | F7: =SUMIF(月次返済!$B$2:$B$421,A7,月次返済!$F$2:$F$421) -> 988353.17 | G7: =INDEX(月次返済!$H$2:$H$421,A7*12) -> 64927075 | H7: =IF(A7<=入力!$B$34,MIN(G7,入力!$B$35)*入力!$B$33,0) -> 245000 | I7: =MAX(0,C7-MIN(1950000,MAX(550000,IF(C7<=1800000,C7*0.4-100000,IF(C7<=3600000,C7*0.3+80000,IF(C7<=6600000,C7*0.2+440000,IF(C7<=8500000,C7*0.1+1100000,1950000))))))-C7*0.145-480000) -> 7454749.5 | J7: =IF(I7<=1950000,I7*0.05,IF(I7<=3300000,I7*0.1-97500,IF(I7<=6950000,I7*0.2-427500,IF(I7<=9000000,I7*0.23-636000,IF(I7<=18000000,I7*0.33-1536000,I7*0.4-2796000))))) -> 1078592.4 | K7: =J7+MIN(97500,I7*0.05) -> 1176092.4 | L7: =MIN(H7,K7) -> 245000 | M7: =12*入力!$B$18*(1+入力!$B$19)^(A7-1) -> 342000 | N7: =12*IF(A7>=入力!$B$23,入力!$C$23,IF(A7>=入力!$B$22,入力!$C$22,IF(A7>=入力!$B$21,入力!$C$21,入力!$B$20))) -> 298800 | O7: =12*(入力!$B$24+入力!$B$25) -> 17160 | P7: =IF(A7<=入力!$B$30,入力!$B$28,入力!$B$29) -> 300000 | Q7: =E7+M7+N7+O7+P7-L7 -> 3475348.1 | R7: =Q7/12 -> 289612.35 | S7: =IF(C7=0,0,E7/C7) -> 0.23893796 | T7: =IF(D7=0,0,Q7/D7) -> 0.40080903 | U7: =SUM($Q$2:Q7) -> 19014376
A8: 7 | B8: =入力!$B$8+A8-1 -> 2032 | C8: =入力!$B$38*(1+入力!$B$39)^(A8-1) -> 11676722 | D8: =C8*入力!$B$40 -> 8757541.2 | E8: =SUMIF(月次返済!$B$2:$B$421,A8,月次返済!$E$2:$E$421) -> 2762388.1 | F8: =SUMIF(月次返済!$B$2:$B$421,A8,月次返済!$F$2:$F$421) -> 961558.94 | G8: =INDEX(月次返済!$H$2:$H$421,A8*12) -> 63126246 | H8: =IF(A8<=入力!$B$34,MIN(G8,入力!$B$35)*入力!$B$33,0) -> 245000 | I8: =MAX(0,C8-MIN(1950000,MAX(550000,IF(C8<=1800000,C8*0.4-100000,IF(C8<=3600000,C8*0.3+80000,IF(C8<=6600000,C8*0.2+440000,IF(C8<=8500000,C8*0.1+1100000,1950000))))))-C8*0.145-480000) -> 7553597 | J8: =IF(I8<=1950000,I8*0.05,IF(I8<=3300000,I8*0.1-97500,IF(I8<=6950000,I8*0.2-427500,IF(I8<=9000000,I8*0.23-636000,IF(I8<=18000000,I8*0.33-1536000,I8*0.4-2796000))))) -> 1101327.3 | K8: =J8+MIN(97500,I8*0.05) -> 1198827.3 | L8: =MIN(H8,K8) -> 245000 | M8: =12*入力!$B$18*(1+入力!$B$19)^(A8-1) -> 342000 | N8: =12*IF(A8>=入力!$B$23,入力!$C$23,IF(A8>=入力!$B$22,入力!$C$22,IF(A8>=入力!$B$21,入力!$C$21,入力!$B$20))) -> 298800 | O8: =12*(入力!$B$24+入力!$B$25) -> 17160 | P8: =IF(A8<=入力!$B$30,入力!$B$28,入力!$B$29) -> 300000 | Q8: =E8+M8+N8+O8+P8-L8 -> 3475348.1 | R8: =Q8/12 -> 289612.35 | S8: =IF(C8=0,0,E8/C8) -> 0.23657224 | T8: =IF(D8=0,0,Q8/D8) -> 0.39684063 | U8: =SUM($Q$2:Q8) -> 22489724
A9: 8 | B9: =入力!$B$8+A9-1 -> 2033 | C9: =入力!$B$38*(1+入力!$B$39)^(A9-1) -> 11793489 | D9: =C9*入力!$B$40 -> 8845116.7 | E9: =SUMIF(月次返済!$B$2:$B$421,A9,月次返済!$E$2:$E$421) -> 2762388.1 | F9: =SUMIF(月次返済!$B$2:$B$421,A9,月次返済!$F$2:$F$421) -> 934360.01 | G9: =INDEX(月次返済!$H$2:$H$421,A9*12) -> 61298218 | H9: =IF(A9<=入力!$B$34,MIN(G9,入力!$B$35)*入力!$B$33,0) -> 245000 | I9: =MAX(0,C9-MIN(1950000,MAX(550000,IF(C9<=1800000,C9*0.4-100000,IF(C9<=3600000,C9*0.3+80000,IF(C9<=6600000,C9*0.2+440000,IF(C9<=8500000,C9*0.1+1100000,1950000))))))-C9*0.145-480000) -> 7653433 | J9: =IF(I9<=1950000,I9*0.05,IF(I9<=3300000,I9*0.1-97500,IF(I9<=6950000,I9*0.2-427500,IF(I9<=9000000,I9*0.23-636000,IF(I9<=18000000,I9*0.33-1536000,I9*0.4-2796000))))) -> 1124289.6 | K9: =J9+MIN(97500,I9*0.05) -> 1221789.6 | L9: =MIN(H9,K9) -> 245000 | M9: =12*入力!$B$18*(1+入力!$B$19)^(A9-1) -> 342000 | N9: =12*IF(A9>=入力!$B$23,入力!$C$23,IF(A9>=入力!$B$22,入力!$C$22,IF(A9>=入力!$B$21,入力!$C$21,入力!$B$20))) -> 298800 | O9: =12*(入力!$B$24+入力!$B$25) -> 17160 | P9: =IF(A9<=入力!$B$30,入力!$B$28,入力!$B$29) -> 300000 | Q9: =E9+M9+N9+O9+P9-L9 -> 3475348.1 | R9: =Q9/12 -> 289612.35 | S9: =IF(C9=0,0,E9/C9) -> 0.23422994 | T9: =IF(D9=0,0,Q9/D9) -> 0.39291151 | U9: =SUM($Q$2:Q9) -> 25965072
A10: 9 | B10: =入力!$B$8+A10-1 -> 2034 | C10: =入力!$B$38*(1+入力!$B$39)^(A10-1) -> 11911424 | D10: =C10*入力!$B$40 -> 8933567.8 | E10: =SUMIF(月次返済!$B$2:$B$421,A10,月次返済!$E$2:$E$421) -> 2762388.1 | F10: =SUMIF(月次返済!$B$2:$B$421,A10,月次返済!$F$2:$F$421) -> 906750.29 | G10: =INDEX(月次返済!$H$2:$H$421,A10*12) -> 59442580 | H10: =IF(A10<=入力!$B$34,MIN(G10,入力!$B$35)*入力!$B$33,0) -> 245000 | I10: =MAX(0,C10-MIN(1950000,MAX(550000,IF(C10<=1800000,C10*0.4-100000,IF(C10<=3600000,C10*0.3+80000,IF(C10<=6600000,C10*0.2+440000,IF(C10<=8500000,C10*0.1+1100000,1950000))))))-C10*0.145-480000) -> 7754267.3 | J10: =IF(I10<=1950000,I10*0.05,IF(I10<=3300000,I10*0.1-97500,IF(I10<=6950000,I10*0.2-427500,IF(I10<=9000000,I10*0.23-636000,IF(I10<=18000000,I10*0.33-1536000,I10*0.4-2796000))))) -> 1147481.5 | K10: =J10+MIN(97500,I10*0.05) -> 1244981.5 | L10: =MIN(H10,K10) -> 245000 | M10: =12*入力!$B$18*(1+入力!$B$19)^(A10-1) -> 342000 | N10: =12*IF(A10>=入力!$B$23,入力!$C$23,IF(A10>=入力!$B$22,入力!$C$22,IF(A10>=入力!$B$21,入力!$C$21,入力!$B$20))) -> 298800 | O10: =12*(入力!$B$24+入力!$B$25) -> 17160 | P10: =IF(A10<=入力!$B$30,入力!$B$28,入力!$B$29) -> 300000 | Q10: =E10+M10+N10+O10+P10-L10 -> 3475348.1 | R10: =Q10/12 -> 289612.35 | S10: =IF(C10=0,0,E10/C10) -> 0.23191083 | T10: =IF(D10=0,0,Q10/D10) -> 0.3890213 | U10: =SUM($Q$2:Q10) -> 29440420
A11: 10 | B11: =入力!$B$8+A11-1 -> 2035 | C11: =入力!$B$38*(1+入力!$B$39)^(A11-1) -> 12030538 | D11: =C11*入力!$B$40 -> 9022903.5 | E11: =SUMIF(月次返済!$B$2:$B$421,A11,月次返済!$E$2:$E$421) -> 2762388.1 | F11: =SUMIF(月次返済!$B$2:$B$421,A11,月次返済!$F$2:$F$421) -> 878723.56 | G11: =INDEX(月次返済!$H$2:$H$421,A11*12) -> 57558916 | H11: =IF(A11<=入力!$B$34,MIN(G11,入力!$B$35)*入力!$B$33,0) -> 245000 | I11: =MAX(0,C11-MIN(1950000,MAX(550000,IF(C11<=1800000,C11*0.4-100000,IF(C11<=3600000,C11*0.3+80000,IF(C11<=6600000,C11*0.2+440000,IF(C11<=8500000,C11*0.1+1100000,1950000))))))-C11*0.145-480000) -> 7856110 | J11: =IF(I11<=1950000,I11*0.05,IF(I11<=3300000,I11*0.1-97500,IF(I11<=6950000,I11*0.2-427500,IF(I11<=9000000,I11*0.23-636000,IF(I11<=18000000,I11*0.33-1536000,I11*0.4-2796000))))) -> 1170905.3 | K11: =J11+MIN(97500,I11*0.05) -> 1268405.3 | L11: =MIN(H11,K11) -> 245000 | M11: =12*入力!$B$18*(1+入力!$B$19)^(A11-1) -> 342000 | N11: =12*IF(A11>=入力!$B$23,入力!$C$23,IF(A11>=入力!$B$22,入力!$C$22,IF(A11>=入力!$B$21,入力!$C$21,入力!$B$20))) -> 298800 | O11: =12*(入力!$B$24+入力!$B$25) -> 17160 | P11: =IF(A11<=入力!$B$30,入力!$B$28,入力!$B$29) -> 300000 | Q11: =E11+M11+N11+O11+P11-L11 -> 3475348.1 | R11: =Q11/12 -> 289612.35 | S11: =IF(C11=0,0,E11/C11) -> 0.22961468 | T11: =IF(D11=0,0,Q11/D11) -> 0.3851696 | U11: =SUM($Q$2:Q11) -> 32915769
A12: 11 | B12: =入力!$B$8+A12-1 -> 2036 | C12: =入力!$B$38*(1+入力!$B$39)^(A12-1) -> 12150843 | D12: =C12*入力!$B$40 -> 9113132.5 | E12: =SUMIF(月次返済!$B$2:$B$421,A12,月次返済!$E$2:$E$421) -> 2927591.5 | F12: =SUMIF(月次返済!$B$2:$B$421,A12,月次返済!$F$2:$F$421) -> 1134803.7 | G12: =INDEX(月次返済!$H$2:$H$421,A12*12) -> 55766128 | H12: =IF(A12<=入力!$B$34,MIN(G12,入力!$B$35)*入力!$B$33,0) -> 245000 | I12: =MAX(0,C12-MIN(1950000,MAX(550000,IF(C12<=1800000,C12*0.4-100000,IF(C12<=3600000,C12*0.3+80000,IF(C12<=6600000,C12*0.2+440000,IF(C12<=8500000,C12*0.1+1100000,1950000))))))-C12*0.145-480000) -> 7958971.1 | J12: =IF(I12<=1950000,I12*0.05,IF(I12<=3300000,I12*0.1-97500,IF(I12<=6950000,I12*0.2-427500,IF(I12<=9000000,I12*0.23-636000,IF(I12<=18000000,I12*0.33-1536000,I12*0.4-2796000))))) -> 1194563.4 | K12: =J12+MIN(97500,I12*0.05) -> 1292063.4 | L12: =MIN(H12,K12) -> 245000 | M12: =12*入力!$B$18*(1+入力!$B$19)^(A12-1) -> 342000 | N12: =12*IF(A12>=入力!$B$23,入力!$C$23,IF(A12>=入力!$B$22,入力!$C$22,IF(A12>=入力!$B$21,入力!$C$21,入力!$B$20))) -> 398400 | O12: =12*(入力!$B$24+入力!$B$25) -> 17160 | P12: =IF(A12<=入力!$B$30,入力!$B$28,入力!$B$29) -> 300000 | Q12: =E12+M12+N12+O12+P12-L12 -> 3740151.5 | R12: =Q12/12 -> 311679.29 | S12: =IF(C12=0,0,E12/C12) -> 0.24093731 | T12: =IF(D12=0,0,Q12/D12) -> 0.41041338 | U12: =SUM($Q$2:Q12) -> 36655920
A13: 12 | B13: =入力!$B$8+A13-1 -> 2037 | C13: =入力!$B$38*(1+入力!$B$39)^(A13-1) -> 12272352 | D13: =C13*入力!$B$40 -> 9204263.9 | E13: =SUMIF(月次返済!$B$2:$B$421,A13,月次返済!$E$2:$E$421) -> 2927591.5 | F13: =SUMIF(月次返済!$B$2:$B$421,A13,月次返済!$F$2:$F$421) -> 1098617.4 | G13: =INDEX(月次返済!$H$2:$H$421,A13*12) -> 53937154 | H13: =IF(A13<=入力!$B$34,MIN(G13,入力!$B$35)*入力!$B$33,0) -> 245000 | I13: =MAX(0,C13-MIN(1950000,MAX(550000,IF(C13<=1800000,C13*0.4-100000,IF(C13<=3600000,C13*0.3+80000,IF(C13<=6600000,C13*0.2+440000,IF(C13<=8500000,C13*0.1+1100000,1950000))))))-C13*0.145-480000) -> 8062860.8 | J13: =IF(I13<=1950000,I13*0.05,IF(I13<=3300000,I13*0.1-97500,IF(I13<=6950000,I13*0.2-427500,IF(I13<=9000000,I13*0.23-636000,IF(I13<=18000000,I13*0.33-1536000,I13*0.4-2796000))))) -> 1218458 | K13: =J13+MIN(97500,I13*0.05) -> 1315958 | L13: =MIN(H13,K13) -> 245000 | M13: =12*入力!$B$18*(1+入力!$B$19)^(A13-1) -> 342000 | N13: =12*IF(A13>=入力!$B$23,入力!$C$23,IF(A13>=入力!$B$22,入力!$C$22,IF(A13>=入力!$B$21,入力!$C$21,入力!$B$20))) -> 398400 | O13: =12*(入力!$B$24+入力!$B$25) -> 17160 | P13: =IF(A13<=入力!$B$30,入力!$B$28,入力!$B$29) -> 300000 | Q13: =E13+M13+N13+O13+P13-L13 -> 3740151.5 | R13: =Q13/12 -> 311679.29 | S13: =IF(C13=0,0,E13/C13) -> 0.23855179 | T13: =IF(D13=0,0,Q13/D13) -> 0.40634988 | U13: =SUM($Q$2:Q13) -> 40396072
... A36: 35 | B36: =入力!$B$8+A36-1 -> 2060 | C36: =入力!$B$38*(1+入力!$B$39)^(A36-1) -> 15428347 | D36: =C36*入力!$B$40 -> 11571260 | E36: =SUMIF(月次返済!$B$2:$B$421,A36,月次返済!$E$2:$E$421) -> 2927591.5 | F36: =SUMIF(月次返済!$B$2:$B$421,A36,月次返済!$F$2:$F$421) -> 31470.432 | G36: =INDEX(月次返済!$H$2:$H$421,A36*12) -> 0 | H36: =IF(A36<=入力!$B$34,MIN(G36,入力!$B$35)*入力!$B$33,0) -> 0 | I36: =MAX(0,C36-MIN(1950000,MAX(550000,IF(C36<=1800000,C36*0.4-100000,IF(C36<=3600000,C36*0.3+80000,IF(C36<=6600000,C36*0.2+440000,IF(C36<=8500000,C36*0.1+1100000,1950000))))))-C36*0.145-480000) -> 10761237 | J36: =IF(I36<=1950000,I36*0.05,IF(I36<=3300000,I36*0.1-97500,IF(I36<=6950000,I36*0.2-427500,IF(I36<=9000000,I36*0.23-636000,IF(I36<=18000000,I36*0.33-1536000,I36*0.4-2796000))))) -> 2015208.1 | K36: =J36+MIN(97500,I36*0.05) -> 2112708.1 | L36: =MIN(H36,K36) -> 0 | M36: =12*入力!$B$18*(1+入力!$B$19)^(A36-1) -> 342000 | N36: =12*IF(A36>=入力!$B$23,入力!$C$23,IF(A36>=入力!$B$22,入力!$C$22,IF(A36>=入力!$B$21,入力!$C$21,入力!$B$20))) -> 448800 | O36: =12*(入力!$B$24+入力!$B$25) -> 17160 | P36: =IF(A36<=入力!$B$30,入力!$B$28,入力!$B$29) -> 300000 | Q36: =E36+M36+N36+O36+P36-L36 -> 4035551.5 | R36: =Q36/12 -> 336295.96 | S36: =IF(C36=0,0,E36/C36) -> 0.18975406 | T36: =IF(D36=0,0,Q36/D36) -> 0.34875644 | U36: =SUM($Q$2:Q36) -> 1.3281756e+08
A37: 35年合計 | E37: =SUM(E2:E36) -> 99873957 | F37: =SUM(F2:F36) -> 23873957 | L37: =SUM(L2:L36) -> 3185000 | M37: =SUM(M2:M36) -> 11970000 | N37: =SUM(N2:N36) -> 13458000 | O37: =SUM(O2:O36) -> 600600 | P37: =SUM(P2:P36) -> 10100000 | Q37: =SUM(Q2:Q36) -> 1.3281756e+08
A38: ※年収列（C列）は数式ですが、特定の年だけ手入力で上書き可能（産休・転職等のシナリオ）。控除は年末残高×0.7%と納税額概算の小さい方。

Sheet サマリー
A1: シミュレーション結果サマリー（自動計算）
A3: A. 初期費用
A4: 初期自己資金 合計（頭金＋諸費用） | B4: =初期費用!B15 -> 5159300
A5: うち諸費用（頭金除く） | B5: =初期費用!B14 -> 5159300
A7: B. 毎月の支払い（初年度）
A8: ローン月返済額（当初金利） | B8: =月次返済!E2 -> 214537.13
A9: 管理費＋修繕積立金＋TV＋ネット（月） | B9: =入力!B18+入力!B20+入力!B24+入力!B25 -> 46530
A10: 固定資産税等（月割） | B10: =入力!B28/12 -> 18333.333
A11: 毎月の住居費トータル（初年度） | B11: =B8+B9+B10 -> 279400.46
A13: C. 35年トータル
A14: 総返済額（金利シナリオ反映） | B14: =年次シミュレーション!E37 -> 99873957
A15: うち総利息 | B15: =年次シミュレーション!F37 -> 23873957
A16: 住宅ローン控除 合計（概算） | B16: =年次シミュレーション!L37 -> 3185000
A17: 管理費・修繕積立金・TV・ネット 合計 | B17: =年次シミュレーション!M37+年次シミュレーション!N37+年次シミュレーション!O37 -> 26028600
A18: 固定資産税等 合計 | B18: =年次シミュレーション!P37 -> 10100000
A19: 35年 住居費合計（控除差引後） | B19: =年次シミュレーション!Q37 -> 1.3281756e+08
A20: 生涯総コスト（初期費用＋35年住居費） | B20: =B4+B19 -> 1.3797686e+08
A22: D. 家計指標（初年度）
A23: 返済負担率（年間返済÷額面年収） | B23: =年次シミュレーション!E2/年次シミュレーション!C2 -> 0.23404051
A24: 住居費負担率（年間住居費÷手取り） | B24: =年次シミュレーション!Q2/年次シミュレーション!D2 -> 0.37670371
A26: E. 金利感応度（35年固定で借りた場合の比較）
A27: 金利 | B27: 月返済額 | C27: 総返済額
A28: 0.01 | B28: =-PMT(A28/12,入力!$B$7*12,入力!$B$6) -> 214537.13 | C28: =B28*入力!$B$7*12 -> 90105595
A29: 0.015 | B29: =-PMT(A29/12,入力!$B$7*12,入力!$B$6) -> 232700.17 | C29: =B29*入力!$B$7*12 -> 97734073
A30: 0.02 | B30: =-PMT(A30/12,入力!$B$7*12,入力!$B$6) -> 251759.7 | C30: =B30*入力!$B$7*12 -> 1.0573908e+08
A32: ※作成日2026-08-23。金利・税制は同日時点の公開情報に基づく。税・控除は簡易計算のため最終判断は専門家に確認。
